{
  "core_exploration": {
    "central_question": "How can we streamline content creation by removing friction from the capture process?",
    "key_tension": "The conflict between perfectionism in initial expression versus rapid information capture",
    "breakthrough_moment": "Realizing that raw voice capture plus AI processing can bypass the paralysis of trying to get wording perfect upfront",
    "edge_of_understanding": "The optimal balance between human intuition and AI assistance in content refinement"
  },
  "conceptual_dna": [
    "Separate capture from refinement - get the raw information out first, polish later",
    "Use AI as a translation layer between messy human thinking and polished output",
    "Remove cognitive friction by eliminating the need to think about formatting during ideation"
  ],
  "pattern_signature": {
    "thinking_style": [
      "experimental-iterative",
      "systems-holistic"
    ],
    "insight_type": "methodology",
    "development_stage": "exploring",
    "confidence_level": 0.3
  },
  "bridge_potential": {
    "domains_connected": [
      "innovation",
      "design",
      "business_strategy"
    ],
    "novel_synthesis": "Voice-first content creation with AI post-processing",
    "cross_domain_pattern": "Separating generation from evaluation phases to optimize creative flow"
  },
  "genius_indicators": {
    "uniqueness_score": 0.4,
    "depth_score": 0.3,
    "generative_potential": 0.6,
    "framework_emergence": 0.3
  },
  "raw_essence": "The key insight is to completely separate the capture phase from the refinement phase in content creation - use voice recording to dump raw thoughts without worrying about structure or wording, then leverage AI to transform the messy transcript into polished content.",
  "embedding_text": "voice recording content creation AI processing workflow optimization capture refinement separation creative flow friction reduction"
}